<SurveyProgram uuid="" schemaVersion="" objectVersion="">
 <Aliases xsi:type="ObjectAlias" authority="">
  <Identifier xsi:type="String64"></Identifier>
  <IdentifierKind xsi:type="AliasIdentifierKindExt"></IdentifierKind>
  <Description xsi:type="String2000"></Description>
  <EffectiveDateTime xsi:type="TimeStamp">2023-05-06T02:10:04Z</EffectiveDateTime>
  <TerminationDateTime xsi:type="TimeStamp">2023-05-06T02:10:04Z</TerminationDateTime>
 </Aliases>
 <Citation xsi:type="Citation">
  <Title xsi:type="String256"></Title>
  <Originator xsi:type="String64"></Originator>
  <Creation xsi:type="TimeStamp">2023-05-06T02:10:04Z</Creation>
  <Format xsi:type="String2000"></Format>
  <Editor xsi:type="String64"></Editor>
  <LastUpdate xsi:type="TimeStamp">2023-05-06T02:10:04Z</LastUpdate>
  <Description xsi:type="String2000"></Description>
  <EditorHistory xsi:type="String64"></EditorHistory>
  <DescriptiveKeywords xsi:type="String2000"></DescriptiveKeywords>
 </Citation>
 <Existence xsi:type="ExistenceKindExt"></Existence>
 <ObjectVersionReason xsi:type="String2000"></ObjectVersionReason>
 <BusinessActivityHistory xsi:type="String64"></BusinessActivityHistory>
 <OSDUIntegration xsi:type="OSDUIntegration">
  <LineageAssertions xsi:type="OSDULineageAssertion">
   <ID xsi:type="String256"></ID>
   <LineageRelationshipKind xsi:type="OSDULineageRelationshipKind">direct</LineageRelationshipKind>
  </LineageAssertions>
  <OwnerGroup xsi:type="String256"></OwnerGroup>
  <ViewerGroup xsi:type="String256"></ViewerGroup>
  <LegalTags xsi:type="String256"></LegalTags>
  <OSDUGeoJSON xsi:type="xsd:string"></OSDUGeoJSON>
  <WGS84Latitude xsi:type="PlaneAngleMeasure" uom="0.001 seca">0.0</WGS84Latitude>
  <WGS84Longitude xsi:type="PlaneAngleMeasure" uom="0.001 seca">0.0</WGS84Longitude>
  <WGS84LocationMetadata xsi:type="OSDUSpatialLocationIntegration">
   <SpatialLocationCoordinatesDate xsi:type="TimeStamp">2023-05-06T02:10:04Z</SpatialLocationCoordinatesDate>
   <QuantitativeAccuracyBand xsi:type="String64"></QuantitativeAccuracyBand>
   <QualitativeSpatialAccuracyType xsi:type="String64"></QualitativeSpatialAccuracyType>
   <CoordinateQualityCheckPerformedBy xsi:type="String64"></CoordinateQualityCheckPerformedBy>
   <CoordinateQualityCheckDateTime xsi:type="TimeStamp">2023-05-06T02:10:04Z</CoordinateQualityCheckDateTime>
   <CoordinateQualityCheckRemark xsi:type="String256"></CoordinateQualityCheckRemark>
   <AppliedOperation xsi:type="String256"></AppliedOperation>
  </WGS84LocationMetadata>
  <Field xsi:type="String64"></Field>
  <Country xsi:type="String64"></Country>
  <State xsi:type="String64"></State>
  <County xsi:type="String64"></County>
  <City xsi:type="String64"></City>
  <Region xsi:type="String64"></Region>
  <District xsi:type="String64"></District>
  <Block xsi:type="String64"></Block>
  <Prospect xsi:type="String64"></Prospect>
  <Play xsi:type="String64"></Play>
  <Basin xsi:type="String64"></Basin>
 </OSDUIntegration>
 <CustomData xsi:type="CustomData">
  <!-- extensibility element(s) -->
 </CustomData>
 <ExtensionNameValue xsi:type="ExtensionNameValue">
  <Name xsi:type="String64"></Name>
  <Value xsi:type="StringMeasure" uom=""></Value>
  <MeasureClass xsi:type="MeasureClass">absorbed dose</MeasureClass>
  <DTim xsi:type="TimeStamp">2023-05-06T02:10:04Z</DTim>
  <Index xsi:type="xsd:long">0</Index>
  <Description xsi:type="String2000"></Description>
 </ExtensionNameValue>
 <ns1:SurveyVer xsi:type="NonNegativeLong">0</ns1:SurveyVer>
 <ns1:Engineer xsi:type="String64"></ns1:Engineer>
 <ns1:Final xsi:type="String64"></ns1:Final>
 <ns1:SurveySection xsi:type="ns1:SurveySection" uid="">
  <ns1:Sequence xsi:type="NonNegativeLong">0</ns1:Sequence>
  <ns1:Name xsi:type="String64"></ns1:Name>
  <ns1:MdInterval xsi:type="MdInterval">
   <Comment xsi:type="String2000"></Comment>
   <MdMin xsi:type="xsd:double">0.0</MdMin>
   <MdMax xsi:type="xsd:double">0.0</MdMax>
   <Uom xsi:type="LengthUomExt"></Uom>
   <Datum xsi:type="DataObjectReference">
<Uuid xsi:type="UuidString"></Uuid>
<ObjectVersion xsi:type="String64"></ObjectVersion>
<QualifiedType xsi:type="QualifiedType"></QualifiedType>
<Title xsi:type="String2000"></Title>
<EnergisticsUri xsi:type="xsd:anyURI">http://www.example.com/schema/anyURI</EnergisticsUri>
<LocatorUrl xsi:type="xsd:anyURI">http://www.example.com/schema/anyURI</LocatorUrl>
<ExtensionNameValue xsi:type="ExtensionNameValue">
 <Name xsi:type="String64"></Name>
 <Value xsi:nil="true"/>
 <MeasureClass xsi:nil="true"/>
 <DTim xsi:nil="true"/>
 <Index xsi:nil="true"/>
 <Description xsi:type="String2000"></Description>
</ExtensionNameValue>
   </Datum>
  </ns1:MdInterval>
  <ns1:SurveyCompany xsi:type="DataObjectReference">
   <Uuid xsi:type="UuidString"></Uuid>
   <ObjectVersion xsi:type="String64"></ObjectVersion>
   <QualifiedType xsi:type="QualifiedType"></QualifiedType>
   <Title xsi:type="String2000"></Title>
   <EnergisticsUri xsi:type="xsd:anyURI">http://www.example.com/schema/anyURI</EnergisticsUri>
   <LocatorUrl xsi:type="xsd:anyURI">http://www.example.com/schema/anyURI</LocatorUrl>
   <ExtensionNameValue xsi:type="ExtensionNameValue">
<Name xsi:type="String64"></Name>
<Value xsi:type="StringMeasure" uom=""></Value>
<MeasureClass xsi:type="MeasureClass">absorbed dose</MeasureClass>
<DTim xsi:type="TimeStamp">2023-05-06T02:10:04Z</DTim>
<Index xsi:type="xsd:long">0</Index>
<Description xsi:type="String2000"></Description>
   </ExtensionNameValue>
  </ns1:SurveyCompany>
  <ns1:NameTool xsi:type="String64"></ns1:NameTool>
  <ns1:TypeTool xsi:type="String64"></ns1:TypeTool>
  <ns1:ModelError xsi:type="DataObjectReference">
   <Uuid xsi:type="UuidString"></Uuid>
   <ObjectVersion xsi:type="String64"></ObjectVersion>
   <QualifiedType xsi:type="QualifiedType"></QualifiedType>
   <Title xsi:type="String2000"></Title>
   <EnergisticsUri xsi:type="xsd:anyURI">http://www.example.com/schema/anyURI</EnergisticsUri>
   <LocatorUrl xsi:type="xsd:anyURI">http://www.example.com/schema/anyURI</LocatorUrl>
   <ExtensionNameValue xsi:type="ExtensionNameValue">
<Name xsi:type="String64"></Name>
<Value xsi:type="StringMeasure" uom=""></Value>
<MeasureClass xsi:type="MeasureClass">absorbed dose</MeasureClass>
<DTim xsi:type="TimeStamp">2023-05-06T02:10:04Z</DTim>
<Index xsi:type="xsd:long">0</Index>
<Description xsi:type="String2000"></Description>
   </ExtensionNameValue>
  </ns1:ModelError>
  <ns1:Overwrite xsi:type="xsd:boolean">false</ns1:Overwrite>
  <ns1:FrequencyMx xsi:type="LengthMeasure" uom="m">0.0</ns1:FrequencyMx>
  <ns1:ItemState xsi:type="ExistenceKind">actual</ns1:ItemState>
  <ns1:Comments xsi:type="String2000"></ns1:Comments>
  <ns1:ExtensionNameValue xsi:type="ExtensionNameValue">
   <Name xsi:type="String64"></Name>
   <Value xsi:type="StringMeasure" uom=""></Value>
   <MeasureClass xsi:type="MeasureClass">absorbed dose</MeasureClass>
   <DTim xsi:type="TimeStamp">2023-05-06T02:10:04Z</DTim>
   <Index xsi:type="xsd:long">0</Index>
   <Description xsi:type="String2000"></Description>
  </ns1:ExtensionNameValue>
 </ns1:SurveySection>
 <ns1:Wellbore xsi:type="DataObjectReference">
  <Uuid xsi:type="UuidString"></Uuid>
  <ObjectVersion xsi:type="String64"></ObjectVersion>
  <QualifiedType xsi:type="QualifiedType"></QualifiedType>
  <Title xsi:type="String2000"></Title>
  <EnergisticsUri xsi:type="xsd:anyURI">http://www.example.com/schema/anyURI</EnergisticsUri>
  <LocatorUrl xsi:type="xsd:anyURI">http://www.example.com/schema/anyURI</LocatorUrl>
  <ExtensionNameValue xsi:type="ExtensionNameValue">
   <Name xsi:type="String64"></Name>
   <Value xsi:type="StringMeasure" uom=""></Value>
   <MeasureClass xsi:type="MeasureClass">absorbed dose</MeasureClass>
   <DTim xsi:type="TimeStamp">2023-05-06T02:10:04Z</DTim>
   <Index xsi:type="xsd:long">0</Index>
   <Description xsi:type="String2000"></Description>
  </ExtensionNameValue>
 </ns1:Wellbore>
</SurveyProgram> 
